{
  "metadata" : {
    "realm" : null,
    "amsterVersion" : "6.5.1",
    "entityType" : "IdRepositoryUser",
    "entityId" : "anonymous",
    "pathParams" : { }
  },
  "data" : {
    "_id" : "anonymous",
    "userPassword" : null,
    "userPassword-encrypted" : "AAAAA0FFUwIQifIt+i2Mc7NYlUGT++ymyGt6WcQ4Jet8+KZKS1CQc+clLFGRgo8IQ4B8oA47NOBn+8VWlq1t8qc=",
    "givenName" : "anonymous",
    "roles" : [ ],
    "dn" : "uid=anonymous,ou=people,",
    "cn" : "anonymous",
    "inetUserStatus" : "Active",
    "sn" : "anonymous",
    "iplanet-am-user-auth-config" : "[Empty]",
    "_type" : {
      "_id" : "user",
      "name" : "User",
      "collection" : true
    }
  }
}